uncms/__init__.py
uncms/admin.py
uncms/apps.py
uncms/checks.py
uncms/conf.py
uncms/forms.py
uncms/html.py
uncms/middleware.py
uncms/robots.py
uncms/sitemaps.py
uncms/utils.py
uncms/views.py
uncms/jinja2/edit-bar/edit_bar.jinja2
uncms/jinja2_environment/__init__.py
uncms/jinja2_environment/all.py
uncms/jinja2_environment/base.py
uncms/jinja2_environment/edit_bar.py
uncms/jinja2_environment/media.py
uncms/jinja2_environment/pages.py
uncms/links/__init__.py
uncms/links/models.py
uncms/links/urls.py
uncms/links/views.py
uncms/links/migrations/0001_initial.py
uncms/links/migrations/0002_auto_20171020_1320.py
uncms/links/migrations/0003_remove_link_new_window.py
uncms/links/migrations/0004_link_permanent_redirect.py
uncms/links/migrations/__init__.py
uncms/links/static/links/img/link.png
uncms/media/__init__.py
uncms/media/admin.py
uncms/media/admin_views.py
uncms/media/apps.py
uncms/media/fields.py
uncms/media/filetypes.py
uncms/media/forms.py
uncms/media/models.py
uncms/media/types.py
uncms/media/urls.py
uncms/media/views.py
uncms/media/widgets.py
uncms/media/migrations/0001_initial.py
uncms/media/migrations/0002_auto_20150713_1408.py
uncms/media/migrations/0003_file_alt_text.py
uncms/media/migrations/0004_auto_20170407_1442.py
uncms/media/migrations/0005_auto_20171107_1537.py
uncms/media/migrations/0006_remove_video_webm.py
uncms/media/migrations/0007_auto_20180801_1419.py
uncms/media/migrations/0008_auto_20180801_1633.py
uncms/media/migrations/0009_auto_20181207_1318.py
uncms/media/migrations/0010_auto_20190523_1638.py
uncms/media/migrations/0011_delete_video.py
uncms/media/migrations/0012_alter_file_options.py
uncms/media/migrations/__init__.py
uncms/media/static/media/css/bulk-add.css
uncms/media/static/media/css/media-list.css
uncms/media/static/media/img/audio-x-generic.png
uncms/media/static/media/img/image-x-generic.png
uncms/media/static/media/img/text-x-generic-template.png
uncms/media/static/media/img/text-x-generic.png
uncms-0.0.14.dist-info/licenses/LICENSE
uncms-0.0.14.dist-info/METADATA
uncms-0.0.14.dist-info/WHEEL
uncms-0.0.14.dist-info/top_level.txt
uncms-0.0.14.dist-info/RECORD
