Metadata-Version: 2.4
Name: uncms
Version: 0.0.14
Summary: A CMS toolkit for Django emphasising simplicity, speed, and familiarity.
Author-email: Lewis Collard <lewiscollard@gmail.com>
Project-URL: homepage, https://uncms.dev/
Project-URL: documentation, https://docs.uncms.dev/
Project-URL: repository, https://github.com/uncms-dev/uncms
Classifier: Development Status :: 3 - Alpha
Classifier: Framework :: Django :: 5.2
Classifier: Intended Audience :: Developers
Classifier: License :: OSI Approved :: BSD License
Requires-Python: >=3.8
License-File: LICENSE
Requires-Dist: Pillow
Requires-Dist: sorl-thumbnail
Requires-Dist: beautifulsoup4
Requires-Dist: django<5.3,>=5.2
Requires-Dist: django-watson
Requires-Dist: django-reversion
Requires-Dist: nh3<1,>=0.2.15
Requires-Dist: python-magic>=0.4.15
Provides-Extra: dev
Requires-Dist: black==25.12.0; extra == "dev"
Requires-Dist: build==0.9.0; extra == "dev"
Requires-Dist: flake8==7.3.0; extra == "dev"
Requires-Dist: factory-boy==3.2.1; extra == "dev"
Requires-Dist: isort==7.0.0; extra == "dev"
Requires-Dist: Jinja2==3.1.3; extra == "dev"
Requires-Dist: psycopg2; extra == "dev"
Requires-Dist: pylint==4.0.4; extra == "dev"
Requires-Dist: pytest==9.0.2; extra == "dev"
Requires-Dist: pytest-cov==7.0.0; extra == "dev"
Requires-Dist: pytest-django==4.5.2; extra == "dev"
Requires-Dist: twine==5.1.1; extra == "dev"
Provides-Extra: jinja2
Requires-Dist: Jinja2<4,>=3.1.3; extra == "jinja2"
Provides-Extra: testhelpers
Requires-Dist: factory-boy==3.3.3; extra == "testhelpers"
Dynamic: license-file
